brukeropus/__init__.py
brukeropus/control/__init__.py
brukeropus/control/dde.py
brukeropus/control/opus.py
brukeropus/file/__init__.py
brukeropus/file/block.py
brukeropus/file/constants.py
brukeropus/file/data.py
brukeropus/file/directory.py
brukeropus/file/file.py
brukeropus/file/labels.py
brukeropus/file/params.py
brukeropus/file/parse.py
brukeropus/file/report.py
brukeropus/file/utils.py
brukeropus-1.4.3.dist-info/LICENSE
brukeropus-1.4.3.dist-info/METADATA
brukeropus-1.4.3.dist-info/WHEEL
brukeropus-1.4.3.dist-info/top_level.txt
brukeropus-1.4.3.dist-info/RECORD
