Metadata-Version: 2.1
Name: brukeropus
Version: 1.4.3
Summary: A python package for communicating with Bruker OPUS spectroscopy software and reading its binary file format.
Author-email: Josh Duran <josh.m.duran@gmail.com>
Project-URL: Homepage, https://github.com/joshduran/brukeropus
Project-URL: Issues, https://github.com/joshduran/brukeropus/issues
Project-URL: Documentation, https://joshduran.github.io/brukeropus/brukeropus.html
Classifier: Programming Language :: Python :: 3
Classifier: License :: OSI Approved :: MIT License
Classifier: Operating System :: OS Independent
Classifier: Topic :: Scientific/Engineering
Requires-Python: >=3.6
License-File: LICENSE
Requires-Dist: numpy
